deltadefi/__init__.py
deltadefi/api.py
deltadefi/error.py
deltadefi/api_resources/__init__.py
deltadefi/api_resources/auth.py
deltadefi/api_resources/validation.py
deltadefi/clients/__init__.py
deltadefi/clients/accounts.py
deltadefi/clients/app.py
deltadefi/clients/client.py
deltadefi/clients/markets.py
deltadefi/clients/orders.py
deltadefi/clients/points.py
deltadefi/clients/websocket.py
deltadefi/constants/__init__.py
deltadefi/constants/constants.py
deltadefi/models/__init__.py
deltadefi/models/models.py
deltadefi/responses/__init__.py
deltadefi/responses/accounts.py
deltadefi/responses/app.py
deltadefi/responses/points.py
deltadefi/responses/responses.py
deltadefi/utils/__init__.py
deltadefi/utils/helpers.py
deltadefi-1.1.1.dist-info/METADATA
deltadefi-1.1.1.dist-info/WHEEL
deltadefi-1.1.1.dist-info/RECORD
