Metadata-Version: 2.4
Name: deltadefi
Version: 1.1.1
Summary: Python SDK for DeltaDeFi protocol.
Author-email: HinsonSIDAN <wongkahinhinson@gmail.com>
License-Expression: Apache-2.0
Keywords: cardano,defi,sdk,trading
Classifier: Development Status :: 3 - Alpha
Classifier: Intended Audience :: Developers
Classifier: License :: OSI Approved :: Apache Software License
Classifier: Natural Language :: English
Classifier: Programming Language :: Python :: 3
Classifier: Programming Language :: Python :: 3.11
Classifier: Programming Language :: Python :: 3.12
Classifier: Programming Language :: Python :: 3.13
Classifier: Topic :: Office/Business :: Financial :: Investment
Classifier: Topic :: Software Development :: Libraries :: Python Modules
Requires-Python: <4.0.0,>3.11
Requires-Dist: certifi>=2024.8.30
Requires-Dist: charset-normalizer>=3.4.0
Requires-Dist: idna>=3.10
Requires-Dist: pycardano>=0.12.3
Requires-Dist: python-dotenv>=0.9.9
Requires-Dist: requests>=2.25.0
Requires-Dist: sidan-gin>=0.1.7
Requires-Dist: urllib3>=2.2.3
Requires-Dist: websockets>=12.0
